{
    "ABM": "A Beautiful Mind",
    "AMH": "American Hustle",
    "APS": "American Psycho",
    "ARR": "Arrival",
    "BTM": "The Batman",
    "BDR": "Baby Driver",
    "BEE": "The Beekeeper",
    "BID": "The Bourne Identity",
    "COM": "The Color of Money",
    "CSN": "Casino",
    "DBC": "Dallas Buyers Club",
    "DJU": "Django Unchained",
    "DN2": "Dune Part Two",
    "DPA": "Dawn of the Planet of the Apes",
    "DPW": "Deadpool & Wolverine",
    "EEO": "Everything Everywhere All at Once",
    "FLG": "Fall Guy",
    "FRG": "Fargo",
    "GD2": "The Godfather Part II",
    "GDF": "The Godfather",
    "GGR": "Glengarry Glen Ross",
    "GWH": "Good Will Hunting",
    "HEA": "Heat",
    "HST": "Hustle",
    "IMG": "The Imitation Game",
    "JWS": "Jaws",
    "KSI": "Kong: Skull Island",
    "LAC": "L.A. Confidential",
    "LOA": "Lawrence of Arabia",
    "LPR": "Looper",
    "MLG": "Molly's Game",
    "MRT": "The Martian",
    "NCF": "No Country For Old Men",
    "OUT": "Once Upon a Time in Hollywood",
    "PDD": "Please Don't Destroy: The Treasure of Foggy Mountain",
    "PST": "Parasite",
    "PUF": "Pulp Fiction",
    "RED": "Reservoir Dogs",
    "ROU": "Rounders",
    "SLT": "Schindler's List",
    "SVN": "Se7en",
    "TRM": "The Terminator",
    "WPA": "War for the Planet of the Apes",
    "WWD": "What We Do in the Shadows",
    "ZDC": "Zodiac"
  }
  